LICENSE
MANIFEST.in
README.md
setup.py
hived/__init__.py
hived/conf.py
hived/log.py
hived/process.py
hived/queue.py
hived/run_module.py
hived/trail.py
hived/worker.py
hived.egg-info/PKG-INFO
hived.egg-info/SOURCES.txt
hived.egg-info/dependency_links.txt
hived.egg-info/entry_points.txt
hived.egg-info/requires.txt
hived.egg-info/top_level.txt