Metadata-Version: 1.1
Name: hived
Version: 0.8.0
Summary: Hived is a library for writing distributed daemons.
Home-page: https://github.com/sievetech/hived
Author: Dalton Barreto
Author-email: daltonmatos@gmail.com
License: UNKNOWN
Platform: UNKNOWN
Classifier: Intended Audience :: Developers
Classifier: License :: OSI Approved :: BSD License
Classifier: Programming Language :: Python
Classifier: Programming Language :: Python :: 2.7
Classifier: Topic :: Software Development
Classifier: Topic :: Software Development :: Libraries
Classifier: Topic :: Software Development :: Libraries :: Python Modules
